setup.py
cqh_adb/__init__.py
cqh_adb/__main__.py
cqh_adb/run.py
cqh_adb.egg-info/PKG-INFO
cqh_adb.egg-info/SOURCES.txt
cqh_adb.egg-info/dependency_links.txt
cqh_adb.egg-info/entry_points.txt
cqh_adb.egg-info/requires.txt
cqh_adb.egg-info/top_level.txt
cqh_adb/app/__init__.py
cqh_adb/app/basic.py
cqh_adb/app/logcat_dispatch.py